altair_viewer/__init__.py
altair_viewer/_event_provider.py
altair_viewer/_scripts.py
altair_viewer/_utils.py
altair_viewer/_viewer.py
altair_viewer/scripts/listing.json
altair_viewer/scripts/vega-5.10.1.js
altair_viewer/scripts/vega-5.21.0.js
altair_viewer/scripts/vega-5.9.2.js
altair_viewer/scripts/vega-embed-6.2.2.js
altair_viewer/scripts/vega-embed-6.20.0.js
altair_viewer/scripts/vega-embed-6.5.2.js
altair_viewer/scripts/vega-lite-4.0.2.js
altair_viewer/scripts/vega-lite-4.17.0.js
altair_viewer/scripts/vega-lite-4.8.1.js
altair_viewer/static/favicon.ico
altair_viewer/tests/__init__.py
altair_viewer/tests/test_entrypoint.py
altair_viewer/tests/test_event_provider.py
altair_viewer/tests/test_scripts.py
altair_viewer/tests/test_utils.py
altair_viewer/tests/test_viewer.py
altair_viewer-0.4.0.dist-info/LICENSE
altair_viewer-0.4.0.dist-info/METADATA
altair_viewer-0.4.0.dist-info/WHEEL
altair_viewer-0.4.0.dist-info/entry_points.txt
altair_viewer-0.4.0.dist-info/top_level.txt
altair_viewer-0.4.0.dist-info/RECORD
